layer_2.v
`timescale 1ns / 1ps

module layer_2 (
    input signed [15:0] n1,     // The hot take from Neuron 1
    input signed [15:0] n2,     // The dissenting opinion from Neuron 2
    input signed [15:0] n3,     // The tie-breaker from Neuron 3
    output reg trigger,         // 1 = CALL STOCKHOLM (Success), 0 = /dev/null (Trash)
    output reg signed [31:0] score // The raw score (kept for debugging my math anxiety)
);

    // --- LAYER 2 WEIGHTS (The Final Bosses) ---
    // Change these values if you want to alter reality.
    wire signed [7:0] w1 = 127;  // How much we trust Neuron 1
    wire signed [7:0] w2 = 128; // Neuron 2 is chil
    wire signed [7:0] w3 = 128; 
    wire signed [7:0] b  = 232;  // The pessimistic bias (guilty until proven innocent)

    always @(*) begin
        // The Grand Calculation: Weighted sum of the previous layer's hard work.
        // We use 32 bits because overflow is for amateurs.
        score = (n1 * w1) + (n2 * w2) + (n3 * w3) + b;

        // --- THE VERDICT (Thresholding) ---
        // If the score is positive, we found something cool.
        // If negative, it's just cosmic background static.
        if (score > 0) 
            trigger = 1'b1; // WE FOUND THE HIGGS! (Or a glitch).
        else 
            trigger = 1'b0; // Nothing to see here. Move along.
    end

endmodule

weights.vh
// AUTOMATICALLY GENERATED - STABILIZED & CHECKED
// Format: Explicit Decimal (e.g. -8'd12)

// --- LAYER 1 ---
localparam signed [7:0] L1_N1_W1 = 8'd127;
localparam signed [7:0] L1_N1_W2 = 8'd127;
localparam signed [7:0] L1_N1_B  = -8'd128;
localparam signed [7:0] L1_N2_W1 = 8'd0;
localparam signed [7:0] L1_N2_W2 = 8'd0;
localparam signed [7:0] L1_N2_B  = -8'd128;
localparam signed [7:0] L1_N3_W1 = -8'd128;
localparam signed [7:0] L1_N3_W2 = -8'd128;
localparam signed [7:0] L1_N3_B  = 8'd127;

// --- LAYER 2 ---
localparam signed [7:0] L2_W1 = 8'd127;
localparam signed [7:0] L2_W2 = 8'd0;
localparam signed [7:0] L2_W3 = -8'd128;
localparam signed [7:0] L2_B  = -8'd14;

neuron.v
`timescale 1ns / 1ps

module neuron (
    input clk,                  // The heart of the system: synchronize everything
    input rst,                  // Reset: Bring everything to zero
    input signed [7:0] x1,      // Input 1 (signed, 8-bit)
    input signed [7:0] x2,      // Input 2
    input signed [7:0] w1,      // weight for Input 1
    input signed [7:0] w2,      // weight for Input 2
    input signed [7:0] b,       // Bias (the basic threshold)
    output reg signed [15:0] y  // Output (16 bits to hold the BIG result)
);

    // Internal variables (wires) for intermediate calculations
    // They must be big enough!
    reg signed [15:0] mult1;
    reg signed [15:0] mult2;
    reg signed [15:0] sum_raw;

    always @(posedge clk or posedge rst) begin
        if (rst) begin
            y <= 0;
            mult1 <= 0;
            mult2 <= 0;
            sum_raw <= 0;
        end else begin
            // STEP 1: Multiplication (Fixed Point)
            // Python: x * w
            mult1 <= x1 * w1;
            mult2 <= x2 * w2;

            // STEP 2: Sum (Accumulate)
            // Python: (x1*w1) + (x2*w2) + bias
            // Note: Bias (8-bit) is automatically extended
            sum_raw <= mult1 + mult2 + b; 

            // STEP 3: ReLU Activation (The "AI" Part)
            // If the sum is negative, the output is 0. Otherwise it is the sum.
            if (sum_raw < 0) 
                y <= 0;
            else 
                y <= sum_raw;
        end
    end

endmodule

layer_1.v
`timescale 1ns / 1ps

module layer_1 (
    input clk,
    input rst,
    input signed [7:0] input_energy,
    input signed [7:0] input_isol,
    output signed [15:0] n1_out,
    output signed [15:0] n2_out,
    output signed [15:0] n3_out
);

    // --- SIDELOADING INTELLIGENCE ---
    // This command tells Verilog: "Stop guessing and read the Python script."
    // It pulls in the 'localparam' definitions generated by master_config.py
    `include "weights.vh"

    // --- PATCHING THE MATRIX (Mapping Params to Wires) ---
    
    // NEURON 1: The First Responder
    wire signed [7:0] w1_1 = L1_N1_W1; // Downloaded from weights.vh
    wire signed [7:0] w1_2 = L1_N1_W2;
    wire signed [7:0] b1   = L1_N1_B;

    // NEURON 2: The Skeptic
    wire signed [7:0] w2_1 = L1_N2_W1;
    wire signed [7:0] w2_2 = L1_N2_W2;
    wire signed [7:0] b2   = L1_N2_B;

    // NEURON 3: The Wildcard
    wire signed [7:0] w3_1 = L1_N3_W1;
    wire signed [7:0] w3_2 = L1_N3_W2;
    wire signed [7:0] b3   = L1_N3_B;

    // --- THE ENGINE ROOM (3 Neurons in a trenchcoat) ---
    neuron N1 (.clk(clk), .rst(rst), .x1(input_energy), .x2(input_isol), .w1(w1_1), .w2(w1_2), .b(b1), .y(n1_out));
    neuron N2 (.clk(clk), .rst(rst), .x1(input_energy), .x2(input_isol), .w1(w2_1), .w2(w2_2), .b(b2), .y(n2_out));
    neuron N3 (.clk(clk), .rst(rst), .x1(input_energy), .x2(input_isol), .w1(w3_1), .w2(w3_2), .b(b3), .y(n3_out));

endmodule

nano_trigger.v
`timescale 1ns / 1ps

module nano_trigger (
    input clk,
    input rst,
    input signed [7:0] energy,    // Input from Calorimeter: How spicy is this particle?
    input signed [7:0] isol,      // Input from Muon Sensor: Social distancing score.
    output trigger                // The "Big Red Button": 1 = Nobel Prize, 0 = Trash.
);

    // Internal spaghetti wires connecting Layer 1 to Layer 2 (The Synapses)
    wire signed [15:0] l1_n1;
    wire signed [15:0] l1_n2;
    wire signed [15:0] l1_n3;
    
    // Debug wire: Because we don't trust our own math yet.
    wire signed [31:0] final_score;

    // --- INSTANTIATING LAYER 1 (The Grunt Work) ---
    // This layer does the heavy lifting, crunching raw numbers.
    layer_1 L1 (
        .clk(clk),
        .rst(rst),
        .input_energy(energy),
        .input_isol(isol),
        .n1_out(l1_n1),
        .n2_out(l1_n2),
        .n3_out(l1_n3)
    );

    // --- INSTANTIATING LAYER 2 (Upper Management) ---
    // Takes the credit for Layer 1's work and makes the final decision.
    layer_2 L2 (
        .n1(l1_n1),
        .n2(l1_n2),
        .n3(l1_n3),
        .trigger(trigger),
        .score(final_score)
    );

endmodule

full_system_tb.v
`timescale 1ns / 1ps

module full_system_tb;

    reg clk;
    reg rst;
    reg signed [7:0] energy;
    reg signed [7:0] isol;
    wire trigger;

    // Instantiating the Beast (The entire chip)
    nano_trigger uut (
        .clk(clk), .rst(rst),
        .energy(energy), .isol(isol),
        .trigger(trigger)
    );

    // The heartbeat. 100MHz of pure anxiety.
    always #5 clk = ~clk;

    initial begin
        // Black box recording. If it crashes, we'll know why.
        $dumpfile("full_trigger.vcd");
        $dumpvars(0, full_system_tb);

        // Factory reset. Wiping its memory before we start interrogation.
        clk = 0; rst = 1; energy = 0; isol = 0;
        #20 rst = 0;

        // --- CASE 1: NOISE (The Boring Stuff) ---
        // Low energy, low isolation. Basically just the universe humming.
        // Expectation: Trigger stays low (0).
        energy = 15; 
        isol = 10;
        #40; // Waiting for the neurons to hold a meeting and vote.

        // --- CASE 2: THE JACKPOT (Higgs?) ---
        // High energy, super clean. 
        // Expectation: Trigger goes HIGH (1). Call Stockholm.
        energy = 110; 
        isol = 90;
        #40;
        
        // --- CASE 3: THE TWILIGHT ZONE ---
        // Mediocre energy, mediocre isolation. 
        // Will it pass? Will it fail? The suspense is terrible.
        energy = 60;
        isol = 40;
        #40;

        $finish; // simulation.kill();
    end
endmodule

full_trigger.vcd
$date
	Fri Jan 16 17:18:29 2026
$end
$version
	Icarus Verilog
$end
$timescale
	1ps
$end
$scope module full_system_tb $end
$var wire 1 ! trigger $end
$var reg 1 " clk $end
$var reg 8 # energy [7:0] $end
$var reg 8 $ isol [7:0] $end
$var reg 1 % rst $end
$scope module uut $end
$var wire 1 " clk $end
$var wire 8 & energy [7:0] $end
$var wire 8 ' isol [7:0] $end
$var wire 1 % rst $end
$var wire 1 ! trigger $end
$var wire 16 ( l1_n3 [15:0] $end
$var wire 16 ) l1_n2 [15:0] $end
$var wire 16 * l1_n1 [15:0] $end
$var wire 32 + final_score [31:0] $end
$scope module L1 $end
$var wire 8 , b1 [7:0] $end
$var wire 8 - b2 [7:0] $end
$var wire 8 . b3 [7:0] $end
$var wire 1 " clk $end
$var wire 8 / input_energy [7:0] $end
$var wire 8 0 input_isol [7:0] $end
$var wire 1 % rst $end
$var wire 8 1 w1_1 [7:0] $end
$var wire 8 2 w1_2 [7:0] $end
$var wire 8 3 w2_1 [7:0] $end
$var wire 8 4 w2_2 [7:0] $end
$var wire 8 5 w3_1 [7:0] $end
$var wire 8 6 w3_2 [7:0] $end
$var wire 16 7 n3_out [15:0] $end
$var wire 16 8 n2_out [15:0] $end
$var wire 16 9 n1_out [15:0] $end
$scope module N1 $end
$var wire 8 : b [7:0] $end
$var wire 1 " clk $end
$var wire 1 % rst $end
$var wire 8 ; w1 [7:0] $end
$var wire 8 < w2 [7:0] $end
$var wire 8 = x1 [7:0] $end
$var wire 8 > x2 [7:0] $end
$var reg 16 ? mult1 [15:0] $end
$var reg 16 @ mult2 [15:0] $end
$var reg 16 A sum_raw [15:0] $end
$var reg 16 B y [15:0] $end
$upscope $end
$scope module N2 $end
$var wire 8 C b [7:0] $end
$var wire 1 " clk $end
$var wire 1 % rst $end
$var wire 8 D w1 [7:0] $end
$var wire 8 E w2 [7:0] $end
$var wire 8 F x1 [7:0] $end
$var wire 8 G x2 [7:0] $end
$var reg 16 H mult1 [15:0] $end
$var reg 16 I mult2 [15:0] $end
$var reg 16 J sum_raw [15:0] $end
$var reg 16 K y [15:0] $end
$upscope $end
$scope module N3 $end
$var wire 8 L b [7:0] $end
$var wire 1 " clk $end
$var wire 1 % rst $end
$var wire 8 M w1 [7:0] $end
$var wire 8 N w2 [7:0] $end
$var wire 8 O x1 [7:0] $end
$var wire 8 P x2 [7:0] $end
$var reg 16 Q mult1 [15:0] $end
$var reg 16 R mult2 [15:0] $end
$var reg 16 S sum_raw [15:0] $end
$var reg 16 T y [15:0] $end
$upscope $end
$upscope $end
$scope module L2 $end
$var wire 8 U b [7:0] $end
$var wire 16 V n1 [15:0] $end
$var wire 16 W n2 [15:0] $end
$var wire 16 X n3 [15:0] $end
$var wire 8 Y w1 [7:0] $end
$var wire 8 Z w2 [7:0] $end
$var wire 8 [ w3 [7:0] $end
$var reg 32 \ score [31:0] $end
$var reg 1 ! trigger $end
$upscope $end
$upscope $end
$upscope $end
$enddefinitions $end
$comment Show the parameter values. $end
$dumpall
$end
#0
$dumpvars
b11111111111111111111111111101000 \
b10000000 [
b10000000 Z
b1111111 Y
b0 X
b0 W
b0 V
b11101000 U
b0 T
b0 S
b0 R
b0 Q
b0 P
b0 O
b111100 N
b11101100 M
b101 L
b0 K
b0 J
b0 I
b0 H
b0 G
b0 F
b11110100 E
b101101 D
b1010 C
b0 B
b0 A
b0 @
b0 ?
b0 >
b0 =
b11011111 <
b1111111 ;
b10000000 :
b0 9
b0 8
b0 7
b111100 6
b11101100 5
b11110100 4
b101101 3
b11011111 2
b1111111 1
b0 0
b0 /
b101 .
b1010 -
b10000000 ,
b11111111111111111111111111101000 +
b0 *
b0 )
b0 (
b0 '
b0 &
1%
b0 $
b0 #
0"
0!
$end
#5000
1"
#10000
0"
#15000
1"
#20000
0"
b1010 $
b1010 '
b1010 0
b1010 >
b1010 G
b1010 P
b1111 #
b1111 &
b1111 /
b1111 =
b1111 F
b1111 O
0%
#25000
b101 S
b1001011000 R
b1111111011010100 Q
b1010 J
b1111111110001000 I
b1010100011 H
b1111111110000000 A
b1111111010110110 @
b11101110001 ?
1"
#30000
0"
#35000
b11111111111111111111100001101000 +
b11111111111111111111100001101000 \
b10110100111 A
b1010 )
b1010 8
b1010 K
b1010 W
b1000110101 J
b101 (
b101 7
b101 T
b101 X
b100110001 S
1"
#40000
0"
#45000
1!
b10001101011000001 +
b10001101011000001 \
b100110001 (
b100110001 7
b100110001 T
b100110001 X
b1000110101 )
b1000110101 8
b1000110101 K
b1000110101 W
b10110100111 *
b10110100111 9
b10110100111 B
b10110100111 V
1"
#50000
0"
#55000
1"
#60000
0"
b1011010 $
b1011010 '
b1011010 0
b1011010 >
b1011010 G
b1011010 P
b1101110 #
b1101110 &
b1101110 /
b1101110 =
b1101110 F
b1101110 O
#65000
b1010100011000 R
b1111011101101000 Q
b1111101111001000 I
b1001101010110 H
b1111010001100110 @
b11011010010010 ?
1"
#70000
0"
#75000
b10101001111000 A
b111100101000 J
b110010000101 S
1"
#80000
0"
#85000
b1110011101011110000 +
b1110011101011110000 \
b110010000101 (
b110010000101 7
b110010000101 T
b110010000101 X
b111100101000 )
b111100101000 8
b111100101000 K
b111100101000 W
b10101001111000 *
b10101001111000 9
b10101001111000 B
b10101001111000 V
1"
#90000
0"
#95000
1"
#100000
0"
b101000 $
b101000 '
b101000 0
b101000 >
b101000 G
b101000 P
b111100 #
b111100 &
b111100 /
b111100 =
b111100 F
b111100 O
#105000
b100101100000 R
b1111101101010000 Q
b1111111000100000 I
b101010001100 H
b1111101011011000 @
b1110111000100 ?
1"
#110000
0"
#115000
b1100000011100 A
b100010110110 J
b10010110101 S
1"
#120000
0"
#125000
b1010100000001001100 +
b1010100000001001100 \
b10010110101 (
b10010110101 7
b10010110101 T
b10010110101 X
b100010110110 )
b100010110110 8
b100010110110 K
b100010110110 W
b1100000011100 *
b1100000011100 9
b1100000011100 B
b1100000011100 V
1"
